{
  "sable": {
    "cargoLock": null,
    "date": null,
    "extract": null,
    "name": "sable",
    "passthru": null,
    "pinned": false,
    "src": {
      "arch": null,
      "finalImageName": null,
      "finalImageTag": null,
      "imageDigest": "sha256:26c428df2d37f242b7a704c4e65b70b8507cc72d398e240fb620ae6ba5d95353",
      "imageName": "ghcr.io/sableclient/sable",
      "imageTag": "1.15.0",
      "os": null,
      "sha256": "sha256-oYmLVSmZzpYyDK5ENlwBa2pCeIH6tTiXN7MsCUTBZq4=",
      "tlsVerify": null
    },
    "version": "1.15.0"
  }
}
