{
    "uzdoom": {
        "cargoLocks": null,
        "date": "2025-11-02",
        "extract": null,
        "name": "uzdoom",
        "passthru": null,
        "pinned": false,
        "src": {
            "deepClone": false,
            "fetchSubmodules": false,
            "leaveDotGit": false,
            "name": null,
            "rev": "9373abe3054e317469e428e2b593ea1b264d30db",
            "sha256": "sha256-ulLVfy/I3nTqjTtpRzbfaj674DHCAvdoIjdigv5whng=",
            "sparseCheckout": [],
            "type": "git",
            "url": "https://github.com/UZDoom/UZDoom"
        },
        "version": "9373abe3054e317469e428e2b593ea1b264d30db"
    }
}