{
  "raze": {
    "cargoLocks": null,
    "date": null,
    "extract": null,
    "name": "raze",
    "passthru": null,
    "pinned": false,
    "src": {
      "deepClone": false,
      "fetchSubmodules": false,
      "leaveDotGit": false,
      "name": null,
      "owner": "ZDoom",
      "repo": "Raze",
      "rev": "1.9.1",
      "sha256": "sha256-lXBH2uLAV7wF/sO5t86EB8gwubWkpm56A6E42wJX68I=",
      "type": "github"
    },
    "version": "1.9.1"
  },
  "zmusic": {
    "cargoLocks": null,
    "date": "2024-02-29",
    "extract": null,
    "name": "zmusic",
    "passthru": null,
    "pinned": false,
    "src": {
      "deepClone": false,
      "fetchSubmodules": false,
      "leaveDotGit": false,
      "name": null,
      "rev": "7476a189755d2665b24a58182640752b82b3a66d",
      "sha256": "sha256-P5YEY/7aXJRRwoXsS5VdHgK3dFMJN66P76mPqYW/RLU=",
      "type": "git",
      "url": "https://github.com/ZDoom/ZMusic"
    },
    "version": "7476a189755d2665b24a58182640752b82b3a66d"
  }
}
