{
  "vgmtrans": {
    "cargoLocks": null,
    "date": "2025-08-06",
    "extract": null,
    "name": "vgmtrans",
    "passthru": null,
    "pinned": false,
    "src": {
      "deepClone": false,
      "fetchSubmodules": true,
      "leaveDotGit": false,
      "name": null,
      "rev": "21a03776242d32cf8515976447674c0415e227fe",
      "sha256": "sha256-fEqH8vN45DAPAqvJ9ldT49jL446tTTarutKA1ZywBvU=",
      "sparseCheckout": [],
      "type": "git",
      "url": "https://github.com/vgmtrans/vgmtrans"
    },
    "version": "21a03776242d32cf8515976447674c0415e227fe"
  }
}
