{
  "nyan-doom": {
    "cargoLocks": null,
    "date": null,
    "extract": null,
    "name": "nyan-doom",
    "passthru": null,
    "pinned": false,
    "src": {
      "deepClone": false,
      "fetchSubmodules": false,
      "leaveDotGit": false,
      "name": null,
      "owner": "andrikpowell",
      "repo": "nyan-doom",
      "rev": "v1.2.4",
      "sha256": "sha256-YvItumWSjH+LOE9rotmcsJciPXmIlw4c3jg8Uc9ys5g=",
      "sparseCheckout": [],
      "type": "github"
    },
    "version": "v1.2.4"
  }
}
