{
    "just-a-sample-bin": {
        "cargoLock": null,
        "date": null,
        "extract": null,
        "name": "just-a-sample-bin",
        "passthru": null,
        "pinned": false,
        "src": {
            "name": null,
            "sha256": "sha256-vgkqzmidEChVZ5IZeCiVKfhBynQ57SpTTzb8t7N5avs=",
            "type": "url",
            "url": "https://github.com/BOBONA/Just-a-Sample/releases/download/v1.3-latest/JAS.Linux.VST3.v1.3.2.zip"
        },
        "version": "v1.3-latest/JAS.Linux.VST3.v1.3.2"
    }
}