{
  "absorb": {
    "cargoLocks": null,
    "date": "2025-09-12",
    "extract": null,
    "name": "absorb",
    "passthru": null,
    "pinned": false,
    "src": {
      "deepClone": false,
      "fetchSubmodules": false,
      "leaveDotGit": false,
      "name": null,
      "rev": "dc340430494213db40c67a04e9796b0462e61363",
      "sha256": "sha256-+nU0+QJ730mVnbqavJCzvTEs1555S0+gYVW+3rhmN2c=",
      "sparseCheckout": [],
      "type": "git",
      "url": "https://github.com/Mrugalla/Absorb"
    },
    "version": "dc340430494213db40c67a04e9796b0462e61363"
  },
  "adsr": {
    "cargoLocks": null,
    "date": "2025-09-15",
    "extract": null,
    "name": "adsr",
    "passthru": null,
    "pinned": false,
    "src": {
      "deepClone": false,
      "fetchSubmodules": false,
      "leaveDotGit": false,
      "name": null,
      "rev": "428545e2840abc6fd2e22cb8046df1be862c3aa5",
      "sha256": "sha256-MBepbiyjPci51k5g0SuDGe4jJgs/bIJgHvnG0LzC6HU=",
      "sparseCheckout": [],
      "type": "git",
      "url": "https://github.com/Mrugalla/ADSR"
    },
    "version": "428545e2840abc6fd2e22cb8046df1be862c3aa5"
  },
  "allhaas": {
    "cargoLocks": null,
    "date": "2025-09-12",
    "extract": null,
    "name": "allhaas",
    "passthru": null,
    "pinned": false,
    "src": {
      "deepClone": false,
      "fetchSubmodules": false,
      "leaveDotGit": false,
      "name": null,
      "rev": "1c897e3ed25c37b6b64a093c42d2363d4b23189f",
      "sha256": "sha256-0YnO0QNiPYFdcw22dVbOyFZlwOLq1orWrEVF7kmk9lE=",
      "sparseCheckout": [],
      "type": "git",
      "url": "https://github.com/Mrugalla/ALLHaas"
    },
    "version": "1c897e3ed25c37b6b64a093c42d2363d4b23189f"
  },
  "hammer-and-meiszel": {
    "cargoLocks": null,
    "date": "2025-10-10",
    "extract": null,
    "name": "hammer-and-meiszel",
    "passthru": null,
    "pinned": false,
    "src": {
      "deepClone": false,
      "fetchSubmodules": false,
      "leaveDotGit": false,
      "name": null,
      "rev": "8ab4654287809054a6e28a17c8d6bb4584f9f284",
      "sha256": "sha256-1tY/vGJnpxs+DVyALIZ6gja4/MhNXkLZLRFSgsaepXk=",
      "sparseCheckout": [],
      "type": "git",
      "url": "https://github.com/Mrugalla/Hammer-and-Meiszel"
    },
    "version": "8ab4654287809054a6e28a17c8d6bb4584f9f284"
  },
  "jif": {
    "cargoLocks": null,
    "date": "2025-09-15",
    "extract": null,
    "name": "jif",
    "passthru": null,
    "pinned": false,
    "src": {
      "deepClone": false,
      "fetchSubmodules": false,
      "leaveDotGit": false,
      "name": null,
      "rev": "d82e0283684b494630b2fee2c3d976f491a68f3e",
      "sha256": "sha256-nAP8ru38FG/vUoFFVgXNZZ8i/5JhmamDMFV4flAoUYw=",
      "sparseCheckout": [],
      "type": "git",
      "url": "https://github.com/Mrugalla/JIF"
    },
    "version": "d82e0283684b494630b2fee2c3d976f491a68f3e"
  },
  "manta": {
    "cargoLocks": null,
    "date": "2024-11-02",
    "extract": null,
    "name": "manta",
    "passthru": null,
    "pinned": false,
    "src": {
      "deepClone": false,
      "fetchSubmodules": false,
      "leaveDotGit": false,
      "name": null,
      "rev": "57a76552853dc3d49341497cd61257f9ed6e81d0",
      "sha256": "sha256-Gclqi3u2W1afOXJdlfLCFLZ5Yfb0jy1cAyy427n0wSw=",
      "sparseCheckout": [],
      "type": "git",
      "url": "https://github.com/Mrugalla/Manta"
    },
    "version": "57a76552853dc3d49341497cd61257f9ed6e81d0"
  },
  "nel-19": {
    "cargoLocks": null,
    "date": "2024-09-08",
    "extract": null,
    "name": "nel-19",
    "passthru": null,
    "pinned": false,
    "src": {
      "deepClone": false,
      "fetchSubmodules": false,
      "leaveDotGit": false,
      "name": null,
      "rev": "eb112420eb8547c419ffd1fe5f66672bb600fe47",
      "sha256": "sha256-+6C54F57BPplWcu8DN8bCzHP9KFeWcUYTA6Y9MP/qwc=",
      "sparseCheckout": [],
      "type": "git",
      "url": "https://github.com/Mrugalla/NEL-19"
    },
    "version": "eb112420eb8547c419ffd1fe5f66672bb600fe47"
  },
  "nelorbit": {
    "cargoLocks": null,
    "date": "2025-09-12",
    "extract": null,
    "name": "nelorbit",
    "passthru": null,
    "pinned": false,
    "src": {
      "deepClone": false,
      "fetchSubmodules": false,
      "leaveDotGit": false,
      "name": null,
      "rev": "9fd3eb30351216e400e09c9e322242a059f0355c",
      "sha256": "sha256-1HlCuO8r0M5UUvF1ZNYXv68MhMy1a/+0Sp4keOl8so4=",
      "sparseCheckout": [],
      "type": "git",
      "url": "https://github.com/Mrugalla/NELOrbit"
    },
    "version": "9fd3eb30351216e400e09c9e322242a059f0355c"
  },
  "overdrive-reneo": {
    "cargoLocks": null,
    "date": "2025-09-15",
    "extract": null,
    "name": "overdrive-reneo",
    "passthru": null,
    "pinned": false,
    "src": {
      "deepClone": false,
      "fetchSubmodules": false,
      "leaveDotGit": false,
      "name": null,
      "rev": "a7ab76e2915a0e68f2e6946d8389ad6e308643ac",
      "sha256": "sha256-UjimeLAxXVFKhClAuirM34xLHzL5FbORUuqiUeH9q38=",
      "sparseCheckout": [],
      "type": "git",
      "url": "https://github.com/Mrugalla/Overdrive-ReNEO"
    },
    "version": "a7ab76e2915a0e68f2e6946d8389ad6e308643ac"
  },
  "perlinnoisemod": {
    "cargoLocks": null,
    "date": "2025-09-15",
    "extract": null,
    "name": "perlinnoisemod",
    "passthru": null,
    "pinned": false,
    "src": {
      "deepClone": false,
      "fetchSubmodules": false,
      "leaveDotGit": false,
      "name": null,
      "rev": "5951a7f8ca94045e09ebbe2757c4a15a91595c46",
      "sha256": "sha256-0g9l8nJyt+JHzp9TJIiTkF3Axfz6Jk/sJDp96WKcNFM=",
      "sparseCheckout": [],
      "type": "git",
      "url": "https://github.com/Mrugalla/PerlinNoiseMod"
    },
    "version": "5951a7f8ca94045e09ebbe2757c4a15a91595c46"
  },
  "pitchglitcher": {
    "cargoLocks": null,
    "date": "2025-09-15",
    "extract": null,
    "name": "pitchglitcher",
    "passthru": null,
    "pinned": false,
    "src": {
      "deepClone": false,
      "fetchSubmodules": false,
      "leaveDotGit": false,
      "name": null,
      "rev": "1c95571b5548f1f0aa7283ebacedb2bdf07c0431",
      "sha256": "sha256-o4p2ZqNPOWiP2tTEShFE3fUhzJXZ5BFxKjI7ulN2t2k=",
      "sparseCheckout": [],
      "type": "git",
      "url": "https://github.com/Mrugalla/PitchGlitcher"
    },
    "version": "1c95571b5548f1f0aa7283ebacedb2bdf07c0431"
  },
  "slew-over": {
    "cargoLocks": null,
    "date": "2025-09-12",
    "extract": null,
    "name": "slew-over",
    "passthru": null,
    "pinned": false,
    "src": {
      "deepClone": false,
      "fetchSubmodules": false,
      "leaveDotGit": false,
      "name": null,
      "rev": "c1d8e253931a10acb7c221960dfa760db964cedd",
      "sha256": "sha256-co/SwY0PLH1zgpk5qI9Y94/M62r+Rr7tNl0XQpKlaeU=",
      "sparseCheckout": [],
      "type": "git",
      "url": "https://github.com/Mrugalla/Slew-Over"
    },
    "version": "c1d8e253931a10acb7c221960dfa760db964cedd"
  },
  "susquash": {
    "cargoLocks": null,
    "date": "2025-09-15",
    "extract": null,
    "name": "susquash",
    "passthru": null,
    "pinned": false,
    "src": {
      "deepClone": false,
      "fetchSubmodules": false,
      "leaveDotGit": false,
      "name": null,
      "rev": "3af376db597195005b655c708483ccce8be49c5f",
      "sha256": "sha256-4t4xJWaYuqfxvSXOGL73JWbyqfr8a4/FT51u7cg0oUs=",
      "sparseCheckout": [],
      "type": "git",
      "url": "https://github.com/Mrugalla/susquash"
    },
    "version": "3af376db597195005b655c708483ccce8be49c5f"
  },
  "xen": {
    "cargoLocks": null,
    "date": "2025-11-05",
    "extract": null,
    "name": "xen",
    "passthru": null,
    "pinned": false,
    "src": {
      "deepClone": false,
      "fetchSubmodules": false,
      "leaveDotGit": false,
      "name": null,
      "rev": "6a91348f365bd12c46c1a286679f9a6c844fa16d",
      "sha256": "sha256-/JwXdp2B2YXbFbYzC2mqeP+mp2rMy7r98tQRp+iocbs=",
      "sparseCheckout": [],
      "type": "git",
      "url": "https://github.com/Mrugalla/Xen"
    },
    "version": "6a91348f365bd12c46c1a286679f9a6c844fa16d"
  }
}
