{
  "clap": {
    "cargoLocks": null,
    "date": null,
    "extract": null,
    "name": "clap",
    "passthru": null,
    "pinned": false,
    "src": {
      "deepClone": false,
      "fetchSubmodules": false,
      "leaveDotGit": false,
      "name": null,
      "owner": "free-audio",
      "repo": "clap",
      "rev": "1.2.6",
      "sha256": "sha256-QyIuuiwFg5DP2Ao/LOKYiBXxKHQ0FbFhssIIUnEQz+c=",
      "sparseCheckout": [],
      "type": "github"
    },
    "version": "1.2.6"
  },
  "clap-helpers": {
    "cargoLocks": null,
    "date": "2025-07-08",
    "extract": null,
    "name": "clap-helpers",
    "passthru": null,
    "pinned": false,
    "src": {
      "deepClone": false,
      "fetchSubmodules": false,
      "leaveDotGit": false,
      "name": null,
      "rev": "4d8c96fd7da2a7a67a91cf87b008643d6ad2c9ba",
      "sha256": "sha256-zZ+wF2/DQHIvCb5+w4t85+KKd5MqHk2J8KS72HDH1/4=",
      "sparseCheckout": [],
      "type": "git",
      "url": "https://github.com/free-audio/clap-helpers.git"
    },
    "version": "4d8c96fd7da2a7a67a91cf87b008643d6ad2c9ba"
  },
  "element": {
    "cargoLocks": null,
    "date": "2025-08-27",
    "extract": null,
    "name": "element",
    "passthru": null,
    "pinned": false,
    "src": {
      "deepClone": false,
      "fetchSubmodules": false,
      "leaveDotGit": true,
      "name": null,
      "rev": "3f779a01916c4cdb5e04dac5f2388cc506db3b3e",
      "sha256": "sha256-/nrgVVox3eY9qRVRaIXdrwuhtTEw/BbAmjc1M/HNswk=",
      "sparseCheckout": [],
      "type": "git",
      "url": "https://github.com/kushview/element"
    },
    "version": "3f779a01916c4cdb5e04dac5f2388cc506db3b3e"
  },
  "juce-element": {
    "cargoLocks": null,
    "date": "2024-06-13",
    "extract": null,
    "name": "juce-element",
    "passthru": null,
    "pinned": false,
    "src": {
      "deepClone": false,
      "fetchSubmodules": false,
      "leaveDotGit": false,
      "name": null,
      "rev": "34b98e72bf4406d6a11c9b81a8a404c1abd5a02e",
      "sha256": "sha256-vdtU5CvKjCtqqbGyMrkdavHkNCb91IERnzySoJXXbwE=",
      "sparseCheckout": [],
      "type": "git",
      "url": "https://gitlab.com/kushview/juce"
    },
    "version": "34b98e72bf4406d6a11c9b81a8a404c1abd5a02e"
  },
  "lvtk": {
    "cargoLocks": null,
    "date": "2025-02-19",
    "extract": null,
    "name": "lvtk",
    "passthru": null,
    "pinned": false,
    "src": {
      "deepClone": false,
      "fetchSubmodules": false,
      "leaveDotGit": false,
      "name": null,
      "rev": "6e5f8d72513f76cc8b11f26a7aeb6a77dbe52923",
      "sha256": "sha256-IXgnOPsOnUSlQXbhbdNk+Qpv9yHb9tWrppAocXsBCi0=",
      "sparseCheckout": [],
      "type": "git",
      "url": "https://github.com/lvtk/lvtk.git"
    },
    "version": "6e5f8d72513f76cc8b11f26a7aeb6a77dbe52923"
  },
  "lvtk-host": {
    "cargoLocks": null,
    "date": "2025-02-01",
    "extract": null,
    "name": "lvtk-host",
    "passthru": null,
    "pinned": false,
    "src": {
      "deepClone": false,
      "fetchSubmodules": false,
      "leaveDotGit": false,
      "name": null,
      "rev": "604e642c65f7a457397d72cb0b99e354f1e48abd",
      "sha256": "sha256-lIP/yyMohNyJB+LEZcG0dW/8KNFq7S85GWkmye+oaiM=",
      "sparseCheckout": [],
      "type": "git",
      "url": "https://github.com/lvtk/lvtk-host.git"
    },
    "version": "604e642c65f7a457397d72cb0b99e354f1e48abd"
  }
}
